ellzaf_ml/__init__.py
ellzaf_ml/ghostfacenetsv2.py
ellzaf_ml/lcff.py
ellzaf_ml/ldnet.py
ellzaf_ml/patchswap.py
ellzaf_ml/spectformer.py
ellzaf_ml/augments/__init__.py
ellzaf_ml/augments/patchswap.py
ellzaf_ml/augments/simmimtransform.py
ellzaf_ml/models/__init__.py
ellzaf_ml/models/bimixmobilenet.py
ellzaf_ml/models/fat.py
ellzaf_ml/models/fatmobilenet.py
ellzaf_ml/models/ghostfacenetsv1.py
ellzaf_ml/models/ghostfacenetsv2.py
ellzaf_ml/models/lcff.py
ellzaf_ml/models/ldnet.py
ellzaf_ml/models/mixmobilenet.py
ellzaf_ml/models/projectordistillation.py
ellzaf_ml/models/simmim.py
ellzaf_ml/models/spectformer.py
ellzaf_ml/models/tinyvitsadapter.py
ellzaf_ml/models/vitsadapter.py
ellzaf_ml/models/vitspectral.py
ellzaf_ml/models/vitspectralrope.py
ellzaf_ml/tools/__init__.py
ellzaf_ml/tools/build_optimizer.py
ellzaf_ml/tools/load_pretrained.py
ellzaf_ml/tools/pytorch_earlystopping.py
ellzaf_ml/tools/save_checkpoint.py
ellzaf_ml-1.4.14.dist-info/LICENSE
ellzaf_ml-1.4.14.dist-info/METADATA
ellzaf_ml-1.4.14.dist-info/WHEEL
ellzaf_ml-1.4.14.dist-info/top_level.txt
ellzaf_ml-1.4.14.dist-info/RECORD
