Metadata-Version: 2.1
Name: ellzaf-ml
Version: 1.4.14
Summary: Ellzaf ML
Home-page: https://github.com/Hazqeel09/ellzaf_ml
Author: Hazqeel Afyq
Author-email: hazqeel9@gmail.com
License: MIT
Keywords: artificial intelligence,machine learning
Classifier: Development Status :: 4 - Beta
Classifier: Intended Audience :: Developers
Classifier: Topic :: Scientific/Engineering :: Artificial Intelligence
Classifier: License :: OSI Approved :: MIT License
Classifier: Programming Language :: Python :: 3.8
Requires-Python: >=3.9
License-File: LICENSE
Requires-Dist: einops >=0.7.0
Requires-Dist: torch >=1.10
Requires-Dist: torchvision
Requires-Dist: mediapipe
Requires-Dist: opencv-python
Requires-Dist: scipy
Requires-Dist: timm >=0.9.0
